[
  {
    "id":1,
    "email": "necati.can@otto.com",
    "name": "Necati",
    "surname" : "CAN",
    "gender" : "Erkek",
    "phone": "0554 996 75 60",
    "category": "Sonkullan",
    "rating": 2
  },
  {
    "id":2,
    "email": "ahmet.ozmis@otto.com",
    "name": "Ahmet",
    "surname" : "OZMİŞ",
    "gender" : "Erkek",
    "phone": "0544 444 44 44",
    "category": "Eczastok",
    "rating": 3
  },
  {
    "id":3,
    "email": "emre.cavdar@otto.com",
    "name": "Tolunay Emre",
    "surname" : "ÇAVDAR",
    "gender" : "Erkek",
    "phone": "0553 586 91 19",
    "category": "Dentstok",
    "rating": 4
  },
  {
    "id":4,
    "email": "fehmi.anac@ottoo.com",
    "name": "Fehmi",
    "surname" : "ANAÇ",
    "gender" : "Erkek",
    "phone": "0551 111 11 11",
    "category": "Vetstok",
    "rating": 5
  }
]
